flowpulse/ExampleConfig.json
flowpulse/WorkItem.py
flowpulse/__init__.py
flowpulse/main.py
flowpulse/services/AzureDevOpsWorkItemService.py
flowpulse/services/ConfigService.py
flowpulse/services/CsvService.py
flowpulse/services/FlowMetricsService.py
flowpulse/services/JiraWorkItemService.py
flowpulse/services/MonteCarloService.py
flowpulse/services/PackageService.py
flowpulse/services/WorkItemFilterService.py
flowpulse/services/WorkItemServiceFactory.py
flowpulse/services/__init__.py
flowpulse/services/logo.png
flowpulse-2.0.6.dist-info/licenses/LICENSE
tests/__init__.py
tests/conftest.py
tests/test_work_item.py
tests/services/__init__.py
tests/services/test_AzureDevOpsWorkItemService.py
tests/services/test_WorkItemFilterService.py
tests/services/test_WorkItemServiceFactory.py
tests/services/test_config_service.py
tests/services/test_csv_service.py
tests/services/test_flow_metrics_service.py
tests/services/test_jira_work_item_service.py
tests/services/test_package_service.py
flowpulse-2.0.6.dist-info/METADATA
flowpulse-2.0.6.dist-info/WHEEL
flowpulse-2.0.6.dist-info/entry_points.txt
flowpulse-2.0.6.dist-info/top_level.txt
flowpulse-2.0.6.dist-info/RECORD
