Metadata-Version: 2.4
Name: flowpulse
Version: 2.0.6
Summary: A package to generate flow metrics charts and run Monte Carlo Simulation based Forecasts based on queries against Jira or Azure DevOps.
Home-page: https://letpeople.work
Author: Let People Work
Author-email: contact@letpeople.work
Classifier: Programming Language :: Python :: 3
Classifier: License :: OSI Approved :: MIT License
Classifier: Operating System :: OS Independent
Requires-Python: >=3.10
License-File: LICENSE
Requires-Dist: requests
Requires-Dist: azure-devops
Requires-Dist: pandas
Requires-Dist: numpy
Requires-Dist: matplotlib
Requires-Dist: adjustText
Dynamic: author
Dynamic: author-email
Dynamic: classifier
Dynamic: description
Dynamic: description-content-type
Dynamic: home-page
Dynamic: license-file
Dynamic: requires-dist
Dynamic: requires-python
Dynamic: summary
